[
    {
        "tweet_count": 1,
        "unique_id": "azwar6102",
        "username": "Azwar Rozali",
        "text": "Sebenarnya presiden Prabowo tidak perlu banyak bicara, yang dibutuhkan rakyat aksi nyata. Menaikkan PPN, menaikkan pajak kendaraan bermotor, menaikkan gaji honorer Rp 500ribu tidak perlu 100 hari. Kenapa kasus-kasus lain diabaikan, pengesahan RUU rampas aset presiden diam.",
        "hashtags": [],
        "created_at": "2025-01-01 03:26:45",
        "retweet_count": 0,
        "favorite_count": 0,
        "reply_count": 0,
        "image_paths": [],
        "sentiment": "Neutral"
    },
    {
        "tweet_count": 2,
        "unique_id": "B_dzoel",
        "username": "°Bang_Dzoel°",
        "text": "Hadiah 100 hari kerja kabinet Merah-Putih @prabowo\n\n1. PPN 12%\n2. Daun kelor pengganti Susu\n3. Judol Peringkat Tertinggi Dunia\n4. Memaafkan Koruptor\n5.\n6.\n7.\n\nMenuju Indonesia Emas\nJayalah Indonesiaku\n\n#100HariKabinetOmon \n\n. https://t.co/AIvUpH6PSu",
        "hashtags": [
            "100HariKabinetOmon"
        ],
        "created_at": "2025-01-01 01:34:19",
        "retweet_count": 12,
        "favorite_count": 28,
        "reply_count": 5,
        "image_paths": [
            "C:\\Users\\hariz\\projects\\tweet_scraping\\images\\media_2_0.jpg"
        ],
        "sentiment": "Neutral"
    },
    {
        "tweet_count": 3,
        "unique_id": "RiskyDeswandi",
        "username": "riskydeswandi28",
        "text": "H-19, penilaian 100 Hari Kerja Pemerintahan Republik Indonesia Kabinet Merah Putih.\n#prabowo",
        "hashtags": [
            "prabowo"
        ],
        "created_at": "2025-01-01 00:17:07",
        "retweet_count": 0,
        "favorite_count": 0,
        "reply_count": 0,
        "image_paths": [],
        "sentiment": "Neutral"
    },
    {
        "tweet_count": 4,
        "unique_id": "AlimyFikri",
        "username": "Singgih",
        "text": "@Dennysiregar7 Baru belum 100 hari sdh bosan sama Prabowo bang @Dennysiregar7 , apa minta diganti bang?",
        "hashtags": [],
        "created_at": "2025-01-01 13:15:48",
        "retweet_count": 0,
        "favorite_count": 0,
        "reply_count": 0,
        "image_paths": [],
        "sentiment": "Negative"
    },
    {
        "tweet_count": 5,
        "unique_id": "DitriRizki_D3",
        "username": "dit_RI",
        "text": "@Mdy_Asmara1701 Blunder Pak Prabowo kok bisa milih dia jadi menteri… nilai 11/100 lagi buat pak Prabowo menuju masa habis 100 hari kerja pertama rezim Prabowo…  mau menangis kok Indonesia dibuat main2 sama penguasa, pendukung &amp; oligarki…",
        "hashtags": [],
        "created_at": "2025-01-01 23:56:41",
        "retweet_count": 0,
        "favorite_count": 9,
        "reply_count": 1,
        "image_paths": [],
        "sentiment": "Neutral"
    }
]